bigschema/__init__.py
bigschema/consts.py
bigschema/io.py
bigschema/logger.py
bigschema/templates.py
bigschema/transformers.py
bigschema/utils.py
bigschema/workflow.py
bigschema/scripts/__init__.py
bigschema/scripts/cli.py
bigschema-1.0.1.dist-info/DESCRIPTION.rst
bigschema-1.0.1.dist-info/METADATA
bigschema-1.0.1.dist-info/RECORD
bigschema-1.0.1.dist-info/WHEEL
bigschema-1.0.1.dist-info/entry_points.txt
bigschema-1.0.1.dist-info/metadata.json
bigschema-1.0.1.dist-info/top_level.txt
