Metadata-Version: 2.0
Name: bigschema
Version: 1.0.1
Summary: bigschema provide primitives for writing more maintainable/readable schemas for bigquery in yamland getting bigquery target output from the specification.
Home-page: https://github.com/danishabdullah/bigschema
Author: Danish Abdullah
Author-email: dev@danishabdullah.com
License: BSD 3 Clause
Keywords: bigschema bigquery json java schema transformation
Platform: UNKNOWN
Classifier: Development Status :: 6 - Mature
Classifier: Intended Audience :: Developers
Classifier: Natural Language :: English
Classifier: Programming Language :: Python :: 3
Classifier: Programming Language :: Python :: 3.3
Classifier: Programming Language :: Python :: 3.4
Classifier: Programming Language :: Python :: 3.5
Requires-Dist: PyYAML (==3.11)
Requires-Dist: click (==6.6)
